keeweb_ghcr/__init__.py
keeweb_ghcr/dicts.py
keeweb_ghcr/generate.py
keeweb_ghcr/main.py
keeweb_ghcr/py.typed
keeweb_ghcr/server.py
keeweb_ghcr/static/favicon.ico
keeweb_ghcr/static/favicon.png
keeweb_ghcr/svg/mark-github.svg
keeweb_ghcr/svg/package-16.svg
keeweb_ghcr/templates/index.j2
keeweb_ghcr-0.5.0.dist-info/METADATA
keeweb_ghcr-0.5.0.dist-info/WHEEL
keeweb_ghcr-0.5.0.dist-info/entry_points.txt
keeweb_ghcr-0.5.0.dist-info/RECORD
