Metadata-Version: 2.1
Name: keeweb_ghcr
Version: 0.5.0
Summary: ghcr.io badge generation
Home-page: https://github.com/keeweb/keeweb-badges-ghcr
License: MIT
Keywords: badge,ghcr,ghcr.io,github-container-registry,github
Author: EuropaServ
Author-email: europaserv@github.com
Requires-Python: >=3.8,<3.13
Classifier: Development Status :: 3 - Alpha
Classifier: License :: OSI Approved :: MIT License
Classifier: Programming Language :: Python :: 3
Classifier: Programming Language :: Python :: 3.8
Classifier: Programming Language :: Python :: 3.9
Classifier: Programming Language :: Python :: 3.10
Classifier: Programming Language :: Python :: 3.11
Classifier: Programming Language :: Python :: 3.12
Classifier: Programming Language :: Python :: 3 :: Only
Classifier: Programming Language :: Python :: Implementation :: CPython
Requires-Dist: anybadge (>=1.9.0,<2.0.0)
Requires-Dist: flask (>=2.1.2,<4.0.0)
Requires-Dist: gunicorn (>=20.1,<24.0)
Requires-Dist: humanfriendly (>=10.0,<11.0)
Requires-Dist: requests (>=2.28.0,<3.0.0)
Requires-Dist: types-humanfriendly (>=10.0,<11.0)
Requires-Dist: types-requests (>=2.28.0,<3.0.0)
Requires-Dist: typing-extensions (>=4.5.0,<5.0.0)
Requires-Dist: waitress (>=3.0.0,<4.0.0)
Project-URL: Repository, https://github.com/keeweb/keeweb-badges-ghcr
